{
  "culture": "zh-Hans",
  "texts": {
    "MyAccount": "我的账户",
    "SamplePageMessage": "Paperbase 模块的示例页面",

    "Paperbase:InvalidDocumentTypeCode": "文档类型代码无效：'{documentTypeCode}'。",
    "Paperbase:ExtractedTextIsImmutable": "已写入提取文本，不允许修改。",
    "Paperbase:DocumentDuplicate": "该文件已经上传过 ({FileName})。",
    "Paperbase:DocumentInRecycleBin": "该文件已在回收站中 ({FileName})。",
    "Permission:Documents.Chat": "文档对话",
    "Permission:Documents.Chat.Create": "新建对话",
    "Permission:Documents.Chat.SendMessage": "发送消息",
    "Permission:Documents.Chat.Delete": "删除对话"
  }
}
